{
  "db_name": "PostgreSQL",
  "query": "SELECT status as \"k!\", COUNT(*) as \"c!\" FROM issues\n           WHERE project_id = ANY($1) GROUP BY status",
  "describe": {
    "columns": [
      {
        "ordinal": 0,
        "name": "k!",
        "type_info": "Int2"
      },
      {
        "ordinal": 1,
        "name": "c!",
        "type_info": "Int8"
      }
    ],
    "parameters": {
      "Left": [
        "UuidArray"
      ]
    },
    "nullable": [
      false,
      null
    ]
  },
  "hash": "577859d993b840666c995ac108ada38d43e3c9288fab187d52fa859a62551ccd"
}
